{
  "name": "ARTICLES",
  "options": {
    "idInjection": false,
    "mssql": {
      "schema": "dbo",
      "table": "ARTICLES"
    }
  },
  "properties": {
    "ARTID": {
      "type": "Number",
      "required": true,
      "length": null,
      "precision": 10,
      "scale": 0,
      "id": 1,
      "mssql": {
        "columnName": "ARTID",
        "dataType": "int",
        "dataLength": null,
        "dataPrecision": 10,
        "dataScale": 0,
        "nullable": "NO"
      }
    },
    "ARTCODE": {
      "type": "String",
      "required": true,
      "length": 25,
      "precision": null,
      "scale": null,
      "mssql": {
        "columnName": "ARTCODE",
        "dataType": "varchar",
        "dataLength": 25,
        "dataPrecision": null,
        "dataScale": null,
        "nullable": "NO"
      }
    },
    "ARTTYPE": {
      "type": "String",
      "required": true,
      "length": 1,
      "precision": null,
      "scale": null,
      "mssql": {
        "columnName": "ARTTYPE",
        "dataType": "char",
        "dataLength": 1,
        "dataPrecision": null,
        "dataScale": null,
        "nullable": "NO"
      }
    },
    "ARTISACTIF": {
      "type": "String",
      "required": true,
      "length": 1,
      "precision": null,
      "scale": null,
      "mssql": {
        "columnName": "ARTISACTIF",
        "dataType": "char",
        "dataLength": 1,
        "dataPrecision": null,
        "dataScale": null,
        "nullable": "NO"
      }
    },
    "AFMID": {
      "type": "Number",
      "required": true,
      "length": null,
      "precision": 10,
      "scale": 0,
      "mssql": {
        "columnName": "AFMID",
        "dataType": "int",
        "dataLength": null,
        "dataPrecision": 10,
        "dataScale": 0,
        "nullable": "NO"
      }
    },
    "FRAID": {
      "type": "Number",
      "required": false,
      "length": null,
      "precision": 10,
      "scale": 0,
      "mssql": {
        "columnName": "FRAID",
        "dataType": "int",
        "dataLength": null,
        "dataPrecision": 10,
        "dataScale": 0,
        "nullable": "YES"
      }
    },
    "ARUIDVENTE": {
      "type": "Number",
      "required": true,
      "length": null,
      "precision": 10,
      "scale": 0,
      "mssql": {
        "columnName": "ARUIDVENTE",
        "dataType": "int",
        "dataLength": null,
        "dataPrecision": 10,
        "dataScale": 0,
        "nullable": "NO"
      }
    },
    "ARTIDSUIVANT": {
      "type": "Number",
      "required": false,
      "length": null,
      "precision": 10,
      "scale": 0,
      "mssql": {
        "columnName": "ARTIDSUIVANT",
        "dataType": "int",
        "dataLength": null,
        "dataPrecision": 10,
        "dataScale": 0,
        "nullable": "YES"
      }
    },
    "ARTISSUBSTITUE": {
      "type": "String",
      "required": true,
      "length": 1,
      "precision": null,
      "scale": null,
      "mssql": {
        "columnName": "ARTISSUBSTITUE",
        "dataType": "char",
        "dataLength": 1,
        "dataPrecision": null,
        "dataScale": null,
        "nullable": "NO"
      }
    },
    "ARTIDSUBSTITUTION": {
      "type": "Number",
      "required": false,
      "length": null,
      "precision": 10,
      "scale": 0,
      "mssql": {
        "columnName": "ARTIDSUBSTITUTION",
        "dataType": "int",
        "dataLength": null,
        "dataPrecision": 10,
        "dataScale": 0,
        "nullable": "YES"
      }
    },
    "ARTDATESUBSTITUTION": {
      "type": "Date",
      "required": false,
      "length": null,
      "precision": null,
      "scale": null,
      "mssql": {
        "columnName": "ARTDATESUBSTITUTION",
        "dataType": "datetime",
        "dataLength": null,
        "dataPrecision": null,
        "dataScale": null,
        "nullable": "YES"
      }
    },
    "ARTISDEFAUTFAM": {
      "type": "String",
      "required": true,
      "length": 1,
      "precision": null,
      "scale": null,
      "mssql": {
        "columnName": "ARTISDEFAUTFAM",
        "dataType": "char",
        "dataLength": 1,
        "dataPrecision": null,
        "dataScale": null,
        "nullable": "NO"
      }
    },
    "ARTDESIGNATION": {
      "type": "String",
      "required": false,
      "length": 255,
      "precision": null,
      "scale": null,
      "mssql": {
        "columnName": "ARTDESIGNATION",
        "dataType": "varchar",
        "dataLength": 255,
        "dataPrecision": null,
        "dataScale": null,
        "nullable": "YES"
      }
    },
    "ARTDESIGNATION2": {
      "type": "String",
      "required": false,
      "length": 255,
      "precision": null,
      "scale": null,
      "mssql": {
        "columnName": "ARTDESIGNATION2",
        "dataType": "varchar",
        "dataLength": 255,
        "dataPrecision": null,
        "dataScale": null,
        "nullable": "YES"
      }
    },
    "ARTCODEBARRE": {
      "type": "String",
      "required": false,
      "length": 20,
      "precision": null,
      "scale": null,
      "mssql": {
        "columnName": "ARTCODEBARRE",
        "dataType": "varchar",
        "dataLength": 20,
        "dataPrecision": null,
        "dataScale": null,
        "nullable": "YES"
      }
    },
    "ARTCEECODE": {
      "type": "String",
      "required": false,
      "length": 3,
      "precision": null,
      "scale": null,
      "mssql": {
        "columnName": "ARTCEECODE",
        "dataType": "varchar",
        "dataLength": 3,
        "dataPrecision": null,
        "dataScale": null,
        "nullable": "YES"
      }
    },
    "ARTCEEPRODUIT": {
      "type": "String",
      "required": false,
      "length": 9,
      "precision": null,
      "scale": null,
      "mssql": {
        "columnName": "ARTCEEPRODUIT",
        "dataType": "varchar",
        "dataLength": 9,
        "dataPrecision": null,
        "dataScale": null,
        "nullable": "YES"
      }
    },
    "ARTSOUSFAMILLE": {
      "type": "String",
      "required": false,
      "length": 50,
      "precision": null,
      "scale": null,
      "mssql": {
        "columnName": "ARTSOUSFAMILLE",
        "dataType": "varchar",
        "dataLength": 50,
        "dataPrecision": null,
        "dataScale": null,
        "nullable": "YES"
      }
    },
    "ARTCATEGORIE": {
      "type": "String",
      "required": false,
      "length": 50,
      "precision": null,
      "scale": null,
      "mssql": {
        "columnName": "ARTCATEGORIE",
        "dataType": "varchar",
        "dataLength": 50,
        "dataPrecision": null,
        "dataScale": null,
        "nullable": "YES"
      }
    },
    "ARTNATURE": {
      "type": "String",
      "required": false,
      "length": 50,
      "precision": null,
      "scale": null,
      "mssql": {
        "columnName": "ARTNATURE",
        "dataType": "varchar",
        "dataLength": 50,
        "dataPrecision": null,
        "dataScale": null,
        "nullable": "YES"
      }
    },
    "ARTCOLLECTION": {
      "type": "String",
      "required": false,
      "length": 50,
      "precision": null,
      "scale": null,
      "mssql": {
        "columnName": "ARTCOLLECTION",
        "dataType": "varchar",
        "dataLength": 50,
        "dataPrecision": null,
        "dataScale": null,
        "nullable": "YES"
      }
    },
    "ARTISSTOCK": {
      "type": "String",
      "required": true,
      "length": 1,
      "precision": null,
      "scale": null,
      "mssql": {
        "columnName": "ARTISSTOCK",
        "dataType": "char",
        "dataLength": 1,
        "dataPrecision": null,
        "dataScale": null,
        "nullable": "NO"
      }
    },
    "ARTISVENDU": {
      "type": "String",
      "required": true,
      "length": 1,
      "precision": null,
      "scale": null,
      "mssql": {
        "columnName": "ARTISVENDU",
        "dataType": "char",
        "dataLength": 1,
        "dataPrecision": null,
        "dataScale": null,
        "nullable": "NO"
      }
    },
    "ARTISFORFAIT": {
      "type": "String",
      "required": true,
      "length": 1,
      "precision": null,
      "scale": null,
      "mssql": {
        "columnName": "ARTISFORFAIT",
        "dataType": "char",
        "dataLength": 1,
        "dataPrecision": null,
        "dataScale": null,
        "nullable": "NO"
      }
    },
    "ARTISSERIE": {
      "type": "String",
      "required": true,
      "length": 1,
      "precision": null,
      "scale": null,
      "mssql": {
        "columnName": "ARTISSERIE",
        "dataType": "char",
        "dataLength": 1,
        "dataPrecision": null,
        "dataScale": null,
        "nullable": "NO"
      }
    },
    "ARTISLOT": {
      "type": "String",
      "required": true,
      "length": 1,
      "precision": null,
      "scale": null,
      "mssql": {
        "columnName": "ARTISLOT",
        "dataType": "char",
        "dataLength": 1,
        "dataPrecision": null,
        "dataScale": null,
        "nullable": "NO"
      }
    },
    "ARTISSTATISTIQUE": {
      "type": "String",
      "required": true,
      "length": 1,
      "precision": null,
      "scale": null,
      "mssql": {
        "columnName": "ARTISSTATISTIQUE",
        "dataType": "char",
        "dataLength": 1,
        "dataPrecision": null,
        "dataScale": null,
        "nullable": "NO"
      }
    },
    "ARTISGARANTIE": {
      "type": "String",
      "required": true,
      "length": 1,
      "precision": null,
      "scale": null,
      "mssql": {
        "columnName": "ARTISGARANTIE",
        "dataType": "char",
        "dataLength": 1,
        "dataPrecision": null,
        "dataScale": null,
        "nullable": "NO"
      }
    },
    "ARTISSOUMISESC": {
      "type": "String",
      "required": true,
      "length": 1,
      "precision": null,
      "scale": null,
      "mssql": {
        "columnName": "ARTISSOUMISESC",
        "dataType": "char",
        "dataLength": 1,
        "dataPrecision": null,
        "dataScale": null,
        "nullable": "NO"
      }
    },
    "ARTISSOUMISCOM": {
      "type": "String",
      "required": true,
      "length": 1,
      "precision": null,
      "scale": null,
      "mssql": {
        "columnName": "ARTISSOUMISCOM",
        "dataType": "char",
        "dataLength": 1,
        "dataPrecision": null,
        "dataScale": null,
        "nullable": "NO"
      }
    },
    "ARTISSOUMISREM": {
      "type": "String",
      "required": true,
      "length": 1,
      "precision": null,
      "scale": null,
      "mssql": {
        "columnName": "ARTISSOUMISREM",
        "dataType": "char",
        "dataLength": 1,
        "dataPrecision": null,
        "dataScale": null,
        "nullable": "NO"
      }
    },
    "ARTLASTPA": {
      "type": "Number",
      "required": true,
      "length": null,
      "precision": 18,
      "scale": 6,
      "mssql": {
        "columnName": "ARTLASTPA",
        "dataType": "numeric",
        "dataLength": null,
        "dataPrecision": 18,
        "dataScale": 6,
        "nullable": "NO"
      }
    },
    "ARTPMP": {
      "type": "Number",
      "required": true,
      "length": null,
      "precision": 18,
      "scale": 6,
      "mssql": {
        "columnName": "ARTPMP",
        "dataType": "numeric",
        "dataLength": null,
        "dataPrecision": 18,
        "dataScale": 6,
        "nullable": "NO"
      }
    },
    "ARTCUMP": {
      "type": "Number",
      "required": true,
      "length": null,
      "precision": 18,
      "scale": 6,
      "mssql": {
        "columnName": "ARTCUMP",
        "dataType": "numeric",
        "dataLength": null,
        "dataPrecision": 18,
        "dataScale": 6,
        "nullable": "NO"
      }
    },
    "ARTSEUILVENTE": {
      "type": "Number",
      "required": true,
      "length": null,
      "precision": 18,
      "scale": 6,
      "mssql": {
        "columnName": "ARTSEUILVENTE",
        "dataType": "numeric",
        "dataLength": null,
        "dataPrecision": 18,
        "dataScale": 6,
        "nullable": "NO"
      }
    },
    "ARTQTEVENTEMINI": {
      "type": "Number",
      "required": true,
      "length": null,
      "precision": 20,
      "scale": 6,
      "mssql": {
        "columnName": "ARTQTEVENTEMINI",
        "dataType": "numeric",
        "dataLength": null,
        "dataPrecision": 20,
        "dataScale": 6,
        "nullable": "NO"
      }
    },
    "ARTPOIDS": {
      "type": "Number",
      "required": true,
      "length": null,
      "precision": 20,
      "scale": 6,
      "mssql": {
        "columnName": "ARTPOIDS",
        "dataType": "numeric",
        "dataLength": null,
        "dataPrecision": 20,
        "dataScale": 6,
        "nullable": "NO"
      }
    },
    "ARTUNITEPOIDS": {
      "type": "Number",
      "required": true,
      "length": null,
      "precision": 10,
      "scale": 0,
      "mssql": {
        "columnName": "ARTUNITEPOIDS",
        "dataType": "int",
        "dataLength": null,
        "dataPrecision": 10,
        "dataScale": 0,
        "nullable": "NO"
      }
    },
    "MEMOID": {
      "type": "Number",
      "required": false,
      "length": null,
      "precision": 10,
      "scale": 0,
      "mssql": {
        "columnName": "MEMOID",
        "dataType": "int",
        "dataLength": null,
        "dataPrecision": 10,
        "dataScale": 0,
        "nullable": "YES"
      }
    },
    "DATECREATE": {
      "type": "Date",
      "required": false,
      "length": null,
      "precision": null,
      "scale": null,
      "mssql": {
        "columnName": "DATECREATE",
        "dataType": "datetime",
        "dataLength": null,
        "dataPrecision": null,
        "dataScale": null,
        "nullable": "YES"
      }
    },
    "DATEUPDATE": {
      "type": "Date",
      "required": false,
      "length": null,
      "precision": null,
      "scale": null,
      "mssql": {
        "columnName": "DATEUPDATE",
        "dataType": "datetime",
        "dataLength": null,
        "dataPrecision": null,
        "dataScale": null,
        "nullable": "YES"
      }
    },
    "USRMODIF": {
      "type": "String",
      "required": false,
      "length": 30,
      "precision": null,
      "scale": null,
      "mssql": {
        "columnName": "USRMODIF",
        "dataType": "varchar",
        "dataLength": 30,
        "dataPrecision": null,
        "dataScale": null,
        "nullable": "YES"
      }
    },
    "ARTQTEACHAT": {
      "type": "Number",
      "required": false,
      "length": null,
      "precision": 20,
      "scale": 6,
      "mssql": {
        "columnName": "ARTQTEACHAT",
        "dataType": "numeric",
        "dataLength": null,
        "dataPrecision": 20,
        "dataScale": 6,
        "nullable": "YES"
      }
    },
    "ARTMODESTOCK": {
      "type": "String",
      "required": false,
      "length": 1,
      "precision": null,
      "scale": null,
      "mssql": {
        "columnName": "ARTMODESTOCK",
        "dataType": "char",
        "dataLength": 1,
        "dataPrecision": null,
        "dataScale": null,
        "nullable": "YES"
      }
    },
    "ARTGARANTIE": {
      "type": "Number",
      "required": false,
      "length": null,
      "precision": 5,
      "scale": 0,
      "mssql": {
        "columnName": "ARTGARANTIE",
        "dataType": "smallint",
        "dataLength": null,
        "dataPrecision": 5,
        "dataScale": 0,
        "nullable": "YES"
      }
    },
    "NUMIDLOT": {
      "type": "Number",
      "required": false,
      "length": null,
      "precision": 10,
      "scale": 0,
      "mssql": {
        "columnName": "NUMIDLOT",
        "dataType": "int",
        "dataLength": null,
        "dataPrecision": 10,
        "dataScale": 0,
        "nullable": "YES"
      }
    },
    "NUMIDSERIE": {
      "type": "Number",
      "required": false,
      "length": null,
      "precision": 10,
      "scale": 0,
      "mssql": {
        "columnName": "NUMIDSERIE",
        "dataType": "int",
        "dataLength": null,
        "dataPrecision": 10,
        "dataScale": 0,
        "nullable": "YES"
      }
    },
    "ARTTYPENOMENCLATURE": {
      "type": "String",
      "required": false,
      "length": 1,
      "precision": null,
      "scale": null,
      "mssql": {
        "columnName": "ARTTYPENOMENCLATURE",
        "dataType": "char",
        "dataLength": 1,
        "dataPrecision": null,
        "dataScale": null,
        "nullable": "YES"
      }
    },
    "ARTISREPORTDES": {
      "type": "String",
      "required": false,
      "length": 1,
      "precision": null,
      "scale": null,
      "mssql": {
        "columnName": "ARTISREPORTDES",
        "dataType": "char",
        "dataLength": 1,
        "dataPrecision": null,
        "dataScale": null,
        "nullable": "YES"
      }
    },
    "ARTDESCRIPTION": {
      "type": "String",
      "required": false,
      "length": 2147483647,
      "precision": null,
      "scale": null,
      "mssql": {
        "columnName": "ARTDESCRIPTION",
        "dataType": "text",
        "dataLength": 2147483647,
        "dataPrecision": null,
        "dataScale": null,
        "nullable": "YES"
      }
    },
    "SOCID": {
      "type": "Number",
      "required": true,
      "length": null,
      "precision": 10,
      "scale": 0,
      "mssql": {
        "columnName": "SOCID",
        "dataType": "int",
        "dataLength": null,
        "dataPrecision": 10,
        "dataScale": 0,
        "nullable": "NO"
      }
    },
    "ARTISPERISSABLE": {
      "type": "String",
      "required": true,
      "length": 1,
      "precision": null,
      "scale": null,
      "mssql": {
        "columnName": "ARTISPERISSABLE",
        "dataType": "char",
        "dataLength": 1,
        "dataPrecision": null,
        "dataScale": null,
        "nullable": "NO"
      }
    },
    "ARTQTEUVISMULTI": {
      "type": "String",
      "required": false,
      "length": 1,
      "precision": null,
      "scale": null,
      "mssql": {
        "columnName": "ARTQTEUVISMULTI",
        "dataType": "char",
        "dataLength": 1,
        "dataPrecision": null,
        "dataScale": null,
        "nullable": "YES"
      }
    },
    "ARTISDIMENSION": {
      "type": "String",
      "required": false,
      "length": 1,
      "precision": null,
      "scale": null,
      "mssql": {
        "columnName": "ARTISDIMENSION",
        "dataType": "char",
        "dataLength": 1,
        "dataPrecision": null,
        "dataScale": null,
        "nullable": "YES"
      }
    },
    "DIOID": {
      "type": "Number",
      "required": false,
      "length": null,
      "precision": 10,
      "scale": 0,
      "mssql": {
        "columnName": "DIOID",
        "dataType": "int",
        "dataLength": null,
        "dataPrecision": 10,
        "dataScale": 0,
        "nullable": "YES"
      }
    },
    "ARTISREPORTDIM": {
      "type": "String",
      "required": false,
      "length": 1,
      "precision": null,
      "scale": null,
      "mssql": {
        "columnName": "ARTISREPORTDIM",
        "dataType": "char",
        "dataLength": 1,
        "dataPrecision": null,
        "dataScale": null,
        "nullable": "YES"
      }
    },
    "ARTVALOMARGE": {
      "type": "String",
      "required": false,
      "length": 2,
      "precision": null,
      "scale": null,
      "mssql": {
        "columnName": "ARTVALOMARGE",
        "dataType": "varchar",
        "dataLength": 2,
        "dataPrecision": null,
        "dataScale": null,
        "nullable": "YES"
      }
    },
    "ARTVOLUME": {
      "type": "Number",
      "required": false,
      "length": null,
      "precision": 20,
      "scale": 6,
      "mssql": {
        "columnName": "ARTVOLUME",
        "dataType": "numeric",
        "dataLength": null,
        "dataPrecision": 20,
        "dataScale": 6,
        "nullable": "YES"
      }
    },
    "ARTUNITEVOLUME": {
      "type": "Number",
      "required": false,
      "length": null,
      "precision": 16,
      "scale": 9,
      "mssql": {
        "columnName": "ARTUNITEVOLUME",
        "dataType": "numeric",
        "dataLength": null,
        "dataPrecision": 16,
        "dataScale": 9,
        "nullable": "YES"
      }
    },
    "ARTDENSITE": {
      "type": "Number",
      "required": false,
      "length": null,
      "precision": 5,
      "scale": 4,
      "mssql": {
        "columnName": "ARTDENSITE",
        "dataType": "numeric",
        "dataLength": null,
        "dataPrecision": 5,
        "dataScale": 4,
        "nullable": "YES"
      }
    },
    "ARTCONTREMARQUE": {
      "type": "String",
      "required": true,
      "length": 3,
      "precision": null,
      "scale": null,
      "mssql": {
        "columnName": "ARTCONTREMARQUE",
        "dataType": "char",
        "dataLength": 3,
        "dataPrecision": null,
        "dataScale": null,
        "nullable": "NO"
      }
    },
    "ARTDEEE": {
      "type": "Number",
      "required": true,
      "length": null,
      "precision": 18,
      "scale": 6,
      "mssql": {
        "columnName": "ARTDEEE",
        "dataType": "numeric",
        "dataLength": null,
        "dataPrecision": 18,
        "dataScale": 6,
        "nullable": "NO"
      }
    },
    "ARTPCB": {
      "type": "Number",
      "required": true,
      "length": null,
      "precision": 10,
      "scale": 0,
      "mssql": {
        "columnName": "ARTPCB",
        "dataType": "int",
        "dataLength": null,
        "dataPrecision": 10,
        "dataScale": 0,
        "nullable": "NO"
      }
    },
    "ARTPCBDESIGNATION": {
      "type": "String",
      "required": false,
      "length": 255,
      "precision": null,
      "scale": null,
      "mssql": {
        "columnName": "ARTPCBDESIGNATION",
        "dataType": "varchar",
        "dataLength": 255,
        "dataPrecision": null,
        "dataScale": null,
        "nullable": "YES"
      }
    },
    "ARTLASTPR": {
      "type": "Number",
      "required": true,
      "length": null,
      "precision": 18,
      "scale": 6,
      "mssql": {
        "columnName": "ARTLASTPR",
        "dataType": "numeric",
        "dataLength": null,
        "dataPrecision": 18,
        "dataScale": 6,
        "nullable": "NO"
      }
    },
    "ARTPRMP": {
      "type": "Number",
      "required": true,
      "length": null,
      "precision": 18,
      "scale": 6,
      "mssql": {
        "columnName": "ARTPRMP",
        "dataType": "numeric",
        "dataLength": null,
        "dataPrecision": 18,
        "dataScale": 6,
        "nullable": "NO"
      }
    },
    "ARTCRUMP": {
      "type": "Number",
      "required": true,
      "length": null,
      "precision": 18,
      "scale": 6,
      "mssql": {
        "columnName": "ARTCRUMP",
        "dataType": "numeric",
        "dataLength": null,
        "dataPrecision": 18,
        "dataScale": 6,
        "nullable": "NO"
      }
    },
    "ARTTPVSENSMVT": {
      "type": "Number",
      "required": false,
      "length": null,
      "precision": 5,
      "scale": 0,
      "mssql": {
        "columnName": "ARTTPVSENSMVT",
        "dataType": "smallint",
        "dataLength": null,
        "dataPrecision": 5,
        "dataScale": 0,
        "nullable": "YES"
      }
    },
    "ARTTPVTYPEMVT": {
      "type": "String",
      "required": false,
      "length": 1,
      "precision": null,
      "scale": null,
      "mssql": {
        "columnName": "ARTTPVTYPEMVT",
        "dataType": "char",
        "dataLength": 1,
        "dataPrecision": null,
        "dataScale": null,
        "nullable": "YES"
      }
    },
    "ARUIDSTOCK": {
      "type": "Number",
      "required": false,
      "length": null,
      "precision": 10,
      "scale": 0,
      "mssql": {
        "columnName": "ARUIDSTOCK",
        "dataType": "int",
        "dataLength": null,
        "dataPrecision": 10,
        "dataScale": 0,
        "nullable": "YES"
      }
    },
    "USRCREATE": {
      "type": "String",
      "required": false,
      "length": 50,
      "precision": null,
      "scale": null,
      "mssql": {
        "columnName": "USRCREATE",
        "dataType": "varchar",
        "dataLength": 50,
        "dataPrecision": null,
        "dataScale": null,
        "nullable": "YES"
      }
    },
    "ARTISUSEINGP": {
      "type": "String",
      "required": true,
      "length": 1,
      "precision": null,
      "scale": null,
      "mssql": {
        "columnName": "ARTISUSEINGP",
        "dataType": "char",
        "dataLength": 1,
        "dataPrecision": null,
        "dataScale": null,
        "nullable": "NO"
      }
    },
    "ARTISECOM": {
      "type": "String",
      "required": false,
      "length": 1,
      "precision": null,
      "scale": null,
      "mssql": {
        "columnName": "ARTISECOM",
        "dataType": "char",
        "dataLength": 1,
        "dataPrecision": null,
        "dataScale": null,
        "nullable": "YES"
      }
    },
    "ARTMARQUE": {
      "type": "String",
      "required": false,
      "length": 50,
      "precision": null,
      "scale": null,
      "mssql": {
        "columnName": "ARTMARQUE",
        "dataType": "varchar",
        "dataLength": 50,
        "dataPrecision": null,
        "dataScale": null,
        "nullable": "YES"
      }
    },
    "ARTCLASSE": {
      "type": "String",
      "required": false,
      "length": 50,
      "precision": null,
      "scale": null,
      "mssql": {
        "columnName": "ARTCLASSE",
        "dataType": "varchar",
        "dataLength": 50,
        "dataPrecision": null,
        "dataScale": null,
        "nullable": "YES"
      }
    },
    "ARTLARGEUR": {
      "type": "Number",
      "required": false,
      "length": null,
      "precision": 20,
      "scale": 6,
      "mssql": {
        "columnName": "ARTLARGEUR",
        "dataType": "numeric",
        "dataLength": null,
        "dataPrecision": 20,
        "dataScale": 6,
        "nullable": "YES"
      }
    },
    "ARTLONGUEUR": {
      "type": "Number",
      "required": false,
      "length": null,
      "precision": 20,
      "scale": 6,
      "mssql": {
        "columnName": "ARTLONGUEUR",
        "dataType": "numeric",
        "dataLength": null,
        "dataPrecision": 20,
        "dataScale": 6,
        "nullable": "YES"
      }
    },
    "ARTHAUTEUR": {
      "type": "Number",
      "required": false,
      "length": null,
      "precision": 20,
      "scale": 6,
      "mssql": {
        "columnName": "ARTHAUTEUR",
        "dataType": "numeric",
        "dataLength": null,
        "dataPrecision": 20,
        "dataScale": 6,
        "nullable": "YES"
      }
    },
    "ARTUNITEDIM": {
      "type": "Number",
      "required": false,
      "length": null,
      "precision": 16,
      "scale": 9,
      "mssql": {
        "columnName": "ARTUNITEDIM",
        "dataType": "numeric",
        "dataLength": null,
        "dataPrecision": 16,
        "dataScale": 9,
        "nullable": "YES"
      }
    },
    "ARTID_DECLINAISON": {
      "type": "Number",
      "required": false,
      "length": null,
      "precision": 10,
      "scale": 0,
      "mssql": {
        "columnName": "ARTID_DECLINAISON",
        "dataType": "int",
        "dataLength": null,
        "dataPrecision": 10,
        "dataScale": 0,
        "nullable": "YES"
      }
    },
    "ARGID_1": {
      "type": "Number",
      "required": false,
      "length": null,
      "precision": 10,
      "scale": 0,
      "mssql": {
        "columnName": "ARGID_1",
        "dataType": "int",
        "dataLength": null,
        "dataPrecision": 10,
        "dataScale": 0,
        "nullable": "YES"
      }
    },
    "ARGID_2": {
      "type": "Number",
      "required": false,
      "length": null,
      "precision": 10,
      "scale": 0,
      "mssql": {
        "columnName": "ARGID_2",
        "dataType": "int",
        "dataLength": null,
        "dataPrecision": 10,
        "dataScale": 0,
        "nullable": "YES"
      }
    },
    "ARGID_3": {
      "type": "Number",
      "required": false,
      "length": null,
      "precision": 10,
      "scale": 0,
      "mssql": {
        "columnName": "ARGID_3",
        "dataType": "int",
        "dataLength": null,
        "dataPrecision": 10,
        "dataScale": 0,
        "nullable": "YES"
      }
    },
    "ARGVID_1": {
      "type": "Number",
      "required": false,
      "length": null,
      "precision": 10,
      "scale": 0,
      "mssql": {
        "columnName": "ARGVID_1",
        "dataType": "int",
        "dataLength": null,
        "dataPrecision": 10,
        "dataScale": 0,
        "nullable": "YES"
      }
    },
    "ARGVID_2": {
      "type": "Number",
      "required": false,
      "length": null,
      "precision": 10,
      "scale": 0,
      "mssql": {
        "columnName": "ARGVID_2",
        "dataType": "int",
        "dataLength": null,
        "dataPrecision": 10,
        "dataScale": 0,
        "nullable": "YES"
      }
    },
    "ARGVID_3": {
      "type": "Number",
      "required": false,
      "length": null,
      "precision": 10,
      "scale": 0,
      "mssql": {
        "columnName": "ARGVID_3",
        "dataType": "int",
        "dataLength": null,
        "dataPrecision": 10,
        "dataScale": 0,
        "nullable": "YES"
      }
    },
    "MODID": {
      "type": "Number",
      "required": false,
      "length": null,
      "precision": 19,
      "scale": 0,
      "mssql": {
        "columnName": "MODID",
        "dataType": "bigint",
        "dataLength": null,
        "dataPrecision": 19,
        "dataScale": 0,
        "nullable": "YES"
      }
    }
  }
}